{
  "$schema": "https://designsystembuilder.dev/schemas/metadata-v1.json",
  "collections": {
    "core": {
      "generators": [
        {
          "generator": {
            "type": "fluidScale",
            "typography": {
              "prefix": "",
              "steps": [
                {
                  "maxPx": 12,
                  "minPx": 12
                },
                {
                  "maxPx": 14,
                  "minPx": 14
                },
                {
                  "maxPx": 18,
                  "minPx": 16
                },
                {
                  "maxPx": 24,
                  "minPx": 18
                },
                {
                  "maxPx": 40,
                  "minPx": 24
                },
                {
                  "maxPx": 120,
                  "minPx": 42
                },
                {
                  "maxPx": 280,
                  "minPx": 80
                },
                {
                  "maxPx": 56,
                  "minPx": 32
                },
                {
                  "maxPx": 72,
                  "minPx": 36
                }
              ],
              "unit": "rem"
            },
            "viewport": {
              "maxWidth": 0,
              "minWidth": 0
            }
          },
          "groupPrefix": "type",
          "id": "87c18757-b0ca-42ec-80a3-1850d5e2c063",
          "type": "typography"
        },
        {
          "generator": {
            "spacing": {
              "baseMax": 24,
              "baseMin": 16,
              "customPairs": [
                {
                  "from": "m",
                  "to": "2xl"
                }
              ],
              "includePairs": true,
              "prefix": "",
              "steps": [
                {
                  "multiplier": 1,
                  "name": "s"
                },
                {
                  "multiplier": 1.5,
                  "name": "m"
                },
                {
                  "multiplier": 2,
                  "name": "l"
                },
                {
                  "multiplier": 2.5,
                  "name": "xl"
                },
                {
                  "multiplier": 3,
                  "name": "2xl"
                },
                {
                  "multiplier": 4,
                  "name": "3xl"
                },
                {
                  "multiplier": 5,
                  "name": "4xl"
                },
                {
                  "multiplier": 6,
                  "name": "5xl"
                },
                {
                  "multiplier": 8,
                  "name": "6xl"
                },
                {
                  "multiplier": 9,
                  "name": "7xl"
                }
              ],
              "unit": "rem"
            },
            "type": "fluidScale",
            "viewport": {
              "maxWidth": 0,
              "minWidth": 0
            }
          },
          "groupPrefix": "space",
          "id": "42c9c8e4-ec28-42a0-af93-5e379be76ffb",
          "type": "spacing"
        },
        {
          "generator": {
            "families": [
              {
                "chroma": {
                  "curve": "linear",
                  "end": 0.14,
                  "overrides": {
                    "500": 0.19399990058247113
                  },
                  "start": 0.03
                },
                "hue": {
                  "curve": "linear",
                  "end": 34,
                  "overrides": {
                    "500": 33.76060223297341
                  },
                  "start": 51
                },
                "lightness": {
                  "curve": "linear",
                  "end": 0.12,
                  "overrides": {
                    "200": 0.8,
                    "500": 0.6212633306810114
                  },
                  "start": 0.96
                },
                "name": "orange"
              },
              {
                "chroma": {
                  "curve": "ease-in-out",
                  "end": 0.15,
                  "overrides": {
                    "400": 0.14
                  },
                  "start": 0.03
                },
                "hue": {
                  "curve": "linear",
                  "end": 77,
                  "overrides": {
                    "400": 77
                  },
                  "start": 85
                },
                "lightness": {
                  "curve": "ease-out",
                  "end": 0.18,
                  "overrides": {
                    "400": 0.81
                  },
                  "start": 0.98
                },
                "name": "yellow"
              },
              {
                "chroma": {
                  "curve": "ease-in-out",
                  "end": 0.21,
                  "overrides": {
                    "400": 0.1836796020020742,
                    "800": 0.2359760756535737
                  },
                  "start": 0.01
                },
                "hue": {
                  "curve": "linear",
                  "end": 257,
                  "overrides": {
                    "400": 248.80661243577464,
                    "800": 264.20616147762985
                  },
                  "start": 218
                },
                "lightness": {
                  "curve": "ease-out",
                  "end": 0.08,
                  "overrides": {
                    "400": 0.6690470948878066,
                    "800": 0.34106984901653875
                  },
                  "start": 0.96
                },
                "name": "blue"
              },
              {
                "chroma": {
                  "curve": "ease-in-out",
                  "end": 0.01,
                  "start": 0.01
                },
                "hue": {
                  "curve": "linear",
                  "end": 313,
                  "start": 320
                },
                "lightness": {
                  "curve": "linear",
                  "end": 0.15,
                  "overrides": {
                    "300": 0.89
                  },
                  "start": 0.99
                },
                "name": "neutrals"
              }
            ],
            "steps": [
              "50",
              "100",
              "200",
              "300",
              "400",
              "500",
              "600",
              "700",
              "800",
              "900",
              "950"
            ],
            "type": "colorScale"
          },
          "groupPrefix": "color",
          "id": "6c644bc9-5433-4c11-8f90-5af41fa8cf7d",
          "type": "color"
        }
      ],
      "kind": "regular",
      "modes": [
        "default"
      ]
    },
    "semantic": {
      "kind": "regular",
      "modes": [
        "default"
      ]
    },
    "theme": {
      "kind": "regular",
      "modes": [
        "orange",
        "blue",
        "yellow"
      ]
    }
  },
  "designSystem": {
    "name": "Tenerife Camp"
  },
  "generatedAt": "2026-04-29T11:40:07.305Z",
  "modes": [
    "default",
    "orange",
    "blue",
    "yellow"
  ],
  "version": "1.0.0"
}